example_texts.py
ktextsurfacewriter.py
setup.cfg
setup.py
tests.py
KTextSurfaceWriter.egg-info/PKG-INFO
KTextSurfaceWriter.egg-info/SOURCES.txt
KTextSurfaceWriter.egg-info/dependency_links.txt
KTextSurfaceWriter.egg-info/entry_points.txt
KTextSurfaceWriter.egg-info/not-zip-safe
KTextSurfaceWriter.egg-info/top_level.txt
docs/HISTORY.txt
docs/README.txt