Metadata-Version: 1.0
Name: KTextSurfaceWriter
Version: 0.1.0
Summary: A PyGame addon for display text over surface with many dimension bounds
Home-page: http://keul.it/develop/python/ktextsurfacewriter/
Author: Keul
Author-email: lucafbb@gmail.com
License: GPL
Keywords: python pygame text surface ktextsurfacewriter library
Platform: UNKNOWN
Classifier: Development Status :: 4 - Beta
Classifier: Intended Audience :: Developers
Classifier: License :: OSI Approved :: GNU General Public License (GPL)
Classifier: Operating System :: OS Independent
Classifier: Programming Language :: Python :: 2.5
Classifier: Topic :: Games/Entertainment
Classifier: Topic :: Multimedia :: Graphics
Classifier: Topic :: Software Development :: Libraries :: Python Modules
Classifier: Topic :: Software Development :: User Interfaces
